{
    "0": [
        3.589025195123172,
        0
    ],
    "1": [
        0.0,
        0
    ],
    "2": [
        0.9677353342950794,
        0
    ],
    "3": [
        2.3552749515968734,
        0
    ],
    "4": [
        3.0022093876245783,
        0
    ],
    "5": [
        0.0,
        0
    ],
    "6": [
        1.0936828254877777,
        0
    ],
    "7": [
        0.0,
        0
    ],
    "8": [
        3.828034575813754,
        0
    ],
    "9": [
        0.0,
        0
    ],
    "10": [
        1.6617577419549643,
        0
    ],
    "11": [
        3.414104925270079,
        0
    ],
    "12": [
        0.5708749204419596,
        0
    ],
    "13": [
        0.9080310673599736,
        0
    ],
    "14": [
        0.7307610399264458,
        0
    ]
}