{
    "0": [
        69.36981576995194,
        0
    ],
    "1": [
        33.818335672214424,
        0
    ],
    "2": [
        45.67324955588208,
        0
    ],
    "3": [
        30.966250077898344,
        0
    ],
    "4": [
        58.60832180353371,
        0
    ],
    "5": [
        43.846025612559394,
        0
    ],
    "6": [
        35.776740409790776,
        0
    ],
    "7": [
        37.675118543535746,
        0
    ],
    "8": [
        52.856336719360556,
        0
    ],
    "9": [
        44.4820485087993,
        0
    ],
    "10": [
        26.843353119263806,
        0
    ],
    "11": [
        47.70087394448093,
        0
    ],
    "12": [
        55.56149235933943,
        0
    ],
    "13": [
        65.27293571267815,
        0
    ],
    "14": [
        27.405548329480556,
        0
    ]
}