{
    "0": [
        231.0355622167667,
        0
    ],
    "1": [
        173.18971158281363,
        0
    ],
    "2": [
        101.6918414916624,
        0
    ],
    "3": [
        81.43939952481541,
        0
    ],
    "4": [
        116.26096577359843,
        0
    ],
    "5": [
        123.21273446308663,
        0
    ],
    "6": [
        156.482632999769,
        0
    ],
    "7": [
        101.01049002041735,
        0
    ],
    "8": [
        148.98740591587054,
        0
    ],
    "9": [
        118.49555580329857,
        0
    ],
    "10": [
        139.4975064410195,
        0
    ],
    "11": [
        142.2382880074681,
        0
    ],
    "12": [
        194.17584363832094,
        0
    ],
    "13": [
        136.67538939452348,
        0
    ],
    "14": [
        107.39895389438121,
        0
    ]
}