{
    "0": [
        170.59779166598864,
        0
    ],
    "1": [
        140.51681621112755,
        0
    ],
    "2": [
        106.94220577451438,
        0
    ],
    "3": [
        196.33372863578373,
        0
    ],
    "4": [
        139.76218660233852,
        0
    ],
    "5": [
        134.78124780766828,
        0
    ],
    "6": [
        124.76954776616574,
        0
    ],
    "7": [
        165.89144947870784,
        0
    ],
    "8": [
        202.43577806496572,
        0
    ],
    "9": [
        99.17233188530294,
        0
    ],
    "10": [
        106.23962482926015,
        0
    ],
    "11": [
        157.79257228762685,
        0
    ],
    "12": [
        118.07071401859832,
        0
    ],
    "13": [
        154.92068402504037,
        0
    ],
    "14": [
        169.43157898629195,
        0
    ]
}