{
    "0": [
        158.2911669821064,
        0
    ],
    "1": [
        120.75236833401308,
        0
    ],
    "2": [
        116.57552596707414,
        0
    ],
    "3": [
        170.7052441550726,
        0
    ],
    "4": [
        156.65992472252913,
        0
    ],
    "5": [
        151.01158829829075,
        0
    ],
    "6": [
        122.87013464010451,
        0
    ],
    "7": [
        112.44118181409506,
        0
    ],
    "8": [
        130.18885573940491,
        0
    ],
    "9": [
        148.7308705730558,
        0
    ],
    "10": [
        111.49391724226136,
        0
    ],
    "11": [
        169.21481126340385,
        0
    ],
    "12": [
        162.5463704492101,
        0
    ],
    "13": [
        133.26642177739527,
        0
    ],
    "14": [
        150.9690474051319,
        0
    ]
}