{
    "0": [
        269.24164206346256,
        0
    ],
    "1": [
        157.10702878945415,
        0
    ],
    "2": [
        144.52450304602667,
        0
    ],
    "3": [
        203.93859982936715,
        0
    ],
    "4": [
        253.12980151845215,
        0
    ],
    "5": [
        157.21011791104362,
        0
    ],
    "6": [
        144.52545989020183,
        0
    ],
    "7": [
        207.68012448224383,
        0
    ],
    "8": [
        188.24770527299495,
        0
    ],
    "9": [
        187.09065795961612,
        0
    ],
    "10": [
        113.88970854582887,
        0
    ],
    "11": [
        317.31739981913177,
        0
    ],
    "12": [
        301.99731818583996,
        0
    ],
    "13": [
        177.08396647972089,
        0
    ],
    "14": [
        177.00157672227652,
        0
    ]
}