{
    "0": [
        2.6814741858648365,
        0
    ],
    "1": [
        2.2190411800766645,
        0
    ],
    "2": [
        1.8610030700974056,
        0
    ],
    "3": [
        3.4818391550036423,
        0
    ],
    "4": [
        2.522621721697706,
        0
    ],
    "5": [
        0.0,
        0
    ],
    "6": [
        0.0,
        0
    ],
    "7": [
        0.5365958749863324,
        0
    ],
    "8": [
        1.0107683327607542,
        0
    ],
    "9": [
        4.269296143792974,
        0
    ],
    "10": [
        0.2500064888198857,
        0
    ],
    "11": [
        0.0,
        0
    ],
    "12": [
        1.9473026141568244,
        0
    ],
    "13": [
        0.5537062534077736,
        0
    ],
    "14": [
        2.00606726596227,
        0
    ]
}