{
    "0": [
        2.8497244830573756,
        0
    ],
    "1": [
        2.1405560622913877,
        0
    ],
    "2": [
        0.5426989356590483,
        0
    ],
    "3": [
        1.9807499220610503,
        0
    ],
    "4": [
        0.38221355925351197,
        0
    ],
    "5": [
        3.6237088054687026,
        0
    ],
    "6": [
        0.0,
        0
    ],
    "7": [
        3.773520859305561,
        0
    ],
    "8": [
        0.0,
        0
    ],
    "9": [
        0.07718186073916236,
        0
    ],
    "10": [
        0.21008241193158428,
        0
    ],
    "11": [
        2.8544431368125815,
        0
    ],
    "12": [
        0.0,
        0
    ],
    "13": [
        1.6418091445475804,
        0
    ],
    "14": [
        0.7818191054816324,
        0
    ]
}