{
    "0": [
        0.0,
        0
    ],
    "1": [
        0.5410091930931163,
        0
    ],
    "2": [
        0.39632257744007715,
        0
    ],
    "3": [
        0.07809165665284545,
        0
    ],
    "4": [
        0.0,
        0
    ],
    "5": [
        2.3533502081081155,
        0
    ],
    "6": [
        2.413107673756437,
        0
    ],
    "7": [
        0.2641575024341375,
        0
    ],
    "8": [
        2.178927809127425,
        0
    ],
    "9": [
        0.1377035963530863,
        0
    ],
    "10": [
        1.2385989284920278,
        0
    ],
    "11": [
        6.386138278172164,
        0
    ],
    "12": [
        1.0037497554879167,
        0
    ],
    "13": [
        0.28115908370511267,
        0
    ],
    "14": [
        0.0,
        0
    ]
}