{
    "0": [
        1.6937035572590382,
        0
    ],
    "1": [
        2.2913604044187488,
        0
    ],
    "2": [
        0.0,
        0
    ],
    "3": [
        0.6659166224244447,
        0
    ],
    "4": [
        0.1736196582861224,
        0
    ],
    "5": [
        7.8782860193317985,
        0
    ],
    "6": [
        1.0411169447472644,
        0
    ],
    "7": [
        0.0,
        0
    ],
    "8": [
        1.4484984572674158,
        0
    ],
    "9": [
        1.806289068987434,
        0
    ],
    "10": [
        2.823598706243238,
        0
    ],
    "11": [
        1.877921724411638,
        0
    ],
    "12": [
        2.060411060027202,
        0
    ],
    "13": [
        0.19694397972101715,
        0
    ],
    "14": [
        1.7274244634851461,
        0
    ]
}