{
    "0": [
        4.207186826231902,
        0
    ],
    "1": [
        1.8164533828344103,
        0
    ],
    "2": [
        1.6144064240881435,
        0
    ],
    "3": [
        0.4196650918828207,
        0
    ],
    "4": [
        0.0,
        0
    ],
    "5": [
        2.7117379855237593,
        0
    ],
    "6": [
        0.43431094332446435,
        0
    ],
    "7": [
        0.0,
        0
    ],
    "8": [
        1.0040730139024683,
        0
    ],
    "9": [
        4.326477863087,
        0
    ],
    "10": [
        0.0,
        0
    ],
    "11": [
        2.5361901744865105,
        0
    ],
    "12": [
        2.704340189591179,
        0
    ],
    "13": [
        0.17190714630549858,
        0
    ],
    "14": [
        0.7625761901969066,
        0
    ]
}