{
    "0": [
        1.7407093057749328,
        0
    ],
    "1": [
        1.4073098273822597,
        0
    ],
    "2": [
        3.549521070307417,
        0
    ],
    "3": [
        2.241514672130096,
        0
    ],
    "4": [
        1.3428622211739634,
        0
    ],
    "5": [
        0.2866180809421553,
        0
    ],
    "6": [
        1.0067683723242622,
        0
    ],
    "7": [
        0.0,
        0
    ],
    "8": [
        0.17934464542230832,
        0
    ],
    "9": [
        4.070457979365085,
        0
    ],
    "10": [
        0.5794073997744359,
        0
    ],
    "11": [
        2.0005909202201986,
        0
    ],
    "12": [
        1.9185624865822741,
        0
    ],
    "13": [
        0.0,
        0
    ],
    "14": [
        1.3013634651671957,
        0
    ]
}