{
    "0": [
        0.26906493974317197,
        0
    ],
    "1": [
        2.9596048669034176,
        0
    ],
    "2": [
        2.5717228870078306,
        0
    ],
    "3": [
        3.7995349400338356,
        0
    ],
    "4": [
        2.47650561983086,
        0
    ],
    "5": [
        2.5629207028897665,
        0
    ],
    "6": [
        0.0,
        0
    ],
    "7": [
        1.6224355441518623,
        0
    ],
    "8": [
        0.0,
        0
    ],
    "9": [
        0.9454963273248536,
        0
    ],
    "10": [
        2.134706614402382,
        0
    ],
    "11": [
        0.0,
        0
    ],
    "12": [
        0.0,
        0
    ],
    "13": [
        0.41977672209891065,
        0
    ],
    "14": [
        2.2701174837560414,
        0
    ]
}