{
    "0": [
        49.67376792604753,
        0
    ],
    "1": [
        53.37731604572338,
        0
    ],
    "2": [
        42.40462828247221,
        0
    ],
    "3": [
        53.290511016545196,
        0
    ],
    "4": [
        43.81115847151528,
        0
    ],
    "5": [
        18.98521400952377,
        0
    ],
    "6": [
        25.59719893615334,
        0
    ],
    "7": [
        37.75527175309561,
        0
    ],
    "8": [
        45.90732630840349,
        0
    ],
    "9": [
        51.42017852850567,
        0
    ],
    "10": [
        52.916244395824116,
        0
    ],
    "11": [
        43.3278137820999,
        0
    ],
    "12": [
        46.97914096399492,
        0
    ],
    "13": [
        38.92913023116291,
        0
    ],
    "14": [
        76.71106895486801,
        0
    ]
}