{
    "0": [
        43.49435188709552,
        0
    ],
    "1": [
        28.991334041610408,
        0
    ],
    "2": [
        28.909561803221848,
        0
    ],
    "3": [
        45.989133781727375,
        0
    ],
    "4": [
        57.86086920028008,
        0
    ],
    "5": [
        48.52250825937925,
        0
    ],
    "6": [
        42.24608505876439,
        0
    ],
    "7": [
        59.948966711636444,
        0
    ],
    "8": [
        41.39153356041652,
        0
    ],
    "9": [
        44.978521466556295,
        0
    ],
    "10": [
        31.51860951646082,
        0
    ],
    "11": [
        65.57945126252925,
        0
    ],
    "12": [
        65.76470439543832,
        0
    ],
    "13": [
        44.84030109167815,
        0
    ],
    "14": [
        55.005015948874195,
        0
    ]
}