{
    "0": [
        69.56036158801597,
        0
    ],
    "1": [
        49.132913363403404,
        0
    ],
    "2": [
        51.50509049004201,
        0
    ],
    "3": [
        44.05404162033674,
        0
    ],
    "4": [
        54.72985051291611,
        0
    ],
    "5": [
        39.90446449253298,
        0
    ],
    "6": [
        41.37868846182599,
        0
    ],
    "7": [
        40.58667544733244,
        0
    ],
    "8": [
        50.4915932883858,
        0
    ],
    "9": [
        34.87494367972325,
        0
    ],
    "10": [
        37.72599437561134,
        0
    ],
    "11": [
        36.77176254554028,
        0
    ],
    "12": [
        40.942101985110696,
        0
    ],
    "13": [
        41.577170811456746,
        0
    ],
    "14": [
        31.186803869718766,
        0
    ]
}