{
    "0": [
        31.30483016617442,
        0
    ],
    "1": [
        43.688464470041026,
        0
    ],
    "2": [
        39.17003324153718,
        0
    ],
    "3": [
        25.04672191444309,
        0
    ],
    "4": [
        32.90254313420129,
        0
    ],
    "5": [
        38.124767236709125,
        0
    ],
    "6": [
        41.891824776934754,
        0
    ],
    "7": [
        33.672566929156666,
        0
    ],
    "8": [
        32.670592747680004,
        0
    ],
    "9": [
        41.42097385696469,
        0
    ],
    "10": [
        63.56813401738033,
        0
    ],
    "11": [
        46.2866008218062,
        0
    ],
    "12": [
        63.10318132697841,
        0
    ],
    "13": [
        59.574488321309595,
        0
    ],
    "14": [
        34.69760044349792,
        0
    ]
}