{
    "0": [
        64.16879193660485,
        0
    ],
    "1": [
        28.486304556694247,
        0
    ],
    "2": [
        46.769798327211475,
        0
    ],
    "3": [
        31.16293984122924,
        0
    ],
    "4": [
        47.658819298297374,
        0
    ],
    "5": [
        48.00931362899268,
        0
    ],
    "6": [
        63.85611398588047,
        0
    ],
    "7": [
        58.748941973718274,
        0
    ],
    "8": [
        33.09218376621183,
        0
    ],
    "9": [
        44.46328178348489,
        0
    ],
    "10": [
        49.5706735397671,
        0
    ],
    "11": [
        46.8119026021224,
        0
    ],
    "12": [
        55.58206167616631,
        0
    ],
    "13": [
        33.3982475341153,
        0
    ],
    "14": [
        32.29626879475353,
        0
    ]
}