{
    "0": [
        77.6494938904371,
        0
    ],
    "1": [
        53.93900542727812,
        0
    ],
    "2": [
        40.75752264095035,
        0
    ],
    "3": [
        37.65925350329193,
        0
    ],
    "4": [
        35.78267135811589,
        0
    ],
    "5": [
        40.79508731394943,
        0
    ],
    "6": [
        62.030763707358986,
        0
    ],
    "7": [
        28.627632789779867,
        0
    ],
    "8": [
        52.81847107728696,
        0
    ],
    "9": [
        37.04916075920713,
        0
    ],
    "10": [
        71.76975394533925,
        0
    ],
    "11": [
        24.237305702829374,
        0
    ],
    "12": [
        50.273954667225304,
        0
    ],
    "13": [
        54.78184001272892,
        0
    ],
    "14": [
        35.4406724779568,
        0
    ]
}