{
    "0": [
        83.85734859228923,
        0
    ],
    "1": [
        44.24068756181843,
        0
    ],
    "2": [
        40.71505573229987,
        0
    ],
    "3": [
        48.00419854940752,
        0
    ],
    "4": [
        45.43142027235616,
        0
    ],
    "5": [
        50.09400085627948,
        0
    ],
    "6": [
        36.297554665596536,
        0
    ],
    "7": [
        47.60618647192947,
        0
    ],
    "8": [
        47.816967319515676,
        0
    ],
    "9": [
        49.49368308594146,
        0
    ],
    "10": [
        40.43768898751697,
        0
    ],
    "11": [
        58.01988051526087,
        0
    ],
    "12": [
        36.21351112275926,
        0
    ],
    "13": [
        41.71997545290117,
        0
    ],
    "14": [
        35.327379873483636,
        0
    ]
}