{
    "0": [
        59.04306152967182,
        0
    ],
    "1": [
        32.69058064589021,
        0
    ],
    "2": [
        40.31895626654695,
        0
    ],
    "3": [
        51.23188356854032,
        0
    ],
    "4": [
        57.66326744117137,
        0
    ],
    "5": [
        50.53019561940046,
        0
    ],
    "6": [
        37.46624143487324,
        0
    ],
    "7": [
        39.363617862382526,
        0
    ],
    "8": [
        47.417486271567874,
        0
    ],
    "9": [
        56.62343787574463,
        0
    ],
    "10": [
        43.27802172063747,
        0
    ],
    "11": [
        39.00231504229523,
        0
    ],
    "12": [
        55.509992039639414,
        0
    ],
    "13": [
        46.17640972610256,
        0
    ],
    "14": [
        29.915641621401747,
        0
    ]
}