{
    "0": [
        29.85543127340093,
        0
    ],
    "1": [
        49.832484662586666,
        0
    ],
    "2": [
        41.70570856795096,
        0
    ],
    "3": [
        44.14252343939916,
        0
    ],
    "4": [
        60.306243680574234,
        0
    ],
    "5": [
        43.006813332538364,
        0
    ],
    "6": [
        61.615205930018156,
        0
    ],
    "7": [
        46.509604783791865,
        0
    ],
    "8": [
        36.136711230713914,
        0
    ],
    "9": [
        44.378106903415805,
        0
    ],
    "10": [
        63.74206436249845,
        0
    ],
    "11": [
        60.172954177942394,
        0
    ],
    "12": [
        42.56145800581806,
        0
    ],
    "13": [
        32.24297661039506,
        0
    ],
    "14": [
        35.65514773315953,
        0
    ]
}