{
    "0": [
        32.69004524302644,
        0
    ],
    "1": [
        53.095265252287604,
        0
    ],
    "2": [
        57.97778703348094,
        0
    ],
    "3": [
        26.14246877125151,
        0
    ],
    "4": [
        57.52626713352309,
        0
    ],
    "5": [
        65.2082345589428,
        0
    ],
    "6": [
        40.479237127163536,
        0
    ],
    "7": [
        36.59352377699181,
        0
    ],
    "8": [
        28.671920221634515,
        0
    ],
    "9": [
        26.266054802590144,
        0
    ],
    "10": [
        46.22618227429185,
        0
    ],
    "11": [
        40.945789640470935,
        0
    ],
    "12": [
        43.370630408424084,
        0
    ],
    "13": [
        54.84458535752688,
        0
    ],
    "14": [
        24.016986817023827,
        0
    ]
}