{
    "0": [
        26.990282082341707,
        0
    ],
    "1": [
        47.84487006116873,
        0
    ],
    "2": [
        78.06240971524804,
        0
    ],
    "3": [
        38.45469154198921,
        0
    ],
    "4": [
        47.82512115721892,
        0
    ],
    "5": [
        35.5484075024821,
        0
    ],
    "6": [
        54.09503620989827,
        0
    ],
    "7": [
        50.1467966474205,
        0
    ],
    "8": [
        53.856823837034156,
        0
    ],
    "9": [
        52.28329190511457,
        0
    ],
    "10": [
        48.717872318832356,
        0
    ],
    "11": [
        46.466363363178246,
        0
    ],
    "12": [
        50.5660474112865,
        0
    ],
    "13": [
        49.91960954708205,
        0
    ],
    "14": [
        58.65139777106053,
        0
    ]
}