{
    "0": [
        54.610093202079796,
        0
    ],
    "1": [
        51.28012582530678,
        0
    ],
    "2": [
        27.424061523817485,
        0
    ],
    "3": [
        34.12807307973636,
        0
    ],
    "4": [
        37.1407033974982,
        0
    ],
    "5": [
        48.647943841495035,
        0
    ],
    "6": [
        57.98842454718739,
        0
    ],
    "7": [
        33.74822054451101,
        0
    ],
    "8": [
        40.8570694038787,
        0
    ],
    "9": [
        52.14658454369577,
        0
    ],
    "10": [
        47.51833934473282,
        0
    ],
    "11": [
        39.39200203902821,
        0
    ],
    "12": [
        48.13165550566513,
        0
    ],
    "13": [
        31.451081994731457,
        0
    ],
    "14": [
        40.346014413685964,
        0
    ]
}