{
    "0": [
        36.45804968088982,
        0
    ],
    "1": [
        46.138859903990756,
        0
    ],
    "2": [
        36.279996043664994,
        0
    ],
    "3": [
        42.91526351412542,
        0
    ],
    "4": [
        55.14320088312586,
        0
    ],
    "5": [
        50.40624131280152,
        0
    ],
    "6": [
        38.694788877624134,
        0
    ],
    "7": [
        51.37274120625279,
        0
    ],
    "8": [
        46.57637475070156,
        0
    ],
    "9": [
        29.816557512113718,
        0
    ],
    "10": [
        40.38872999411344,
        0
    ],
    "11": [
        38.69136774675105,
        0
    ],
    "12": [
        48.772909472790296,
        0
    ],
    "13": [
        41.41176229416468,
        0
    ],
    "14": [
        56.00903747669315,
        0
    ]
}