{
    "0": [
        154.86451650217015,
        0
    ],
    "1": [
        151.15541216068058,
        0
    ],
    "2": [
        134.70255521256624,
        0
    ],
    "3": [
        195.48582705855975,
        0
    ],
    "4": [
        127.36944297216456,
        0
    ],
    "5": [
        151.14938692846442,
        0
    ],
    "6": [
        106.0222211875839,
        0
    ],
    "7": [
        114.96945696549236,
        0
    ],
    "8": [
        154.99871376553386,
        0
    ],
    "9": [
        119.92905264820587,
        0
    ],
    "10": [
        104.27556320815738,
        0
    ],
    "11": [
        82.6183226616501,
        0
    ],
    "12": [
        186.48673244737387,
        0
    ],
    "13": [
        132.90031794813314,
        0
    ],
    "14": [
        145.34898009783845,
        0
    ]
}