{
    "0": [
        183.62934972744202,
        0
    ],
    "1": [
        104.72265821920342,
        0
    ],
    "2": [
        115.46328959370602,
        0
    ],
    "3": [
        107.05653938870157,
        0
    ],
    "4": [
        128.2033688995102,
        0
    ],
    "5": [
        127.7958915385707,
        0
    ],
    "6": [
        136.97101763806245,
        0
    ],
    "7": [
        160.65343376385232,
        0
    ],
    "8": [
        148.79453325336107,
        0
    ],
    "9": [
        109.33878542144377,
        0
    ],
    "10": [
        119.26001310961493,
        0
    ],
    "11": [
        241.50016710913792,
        0
    ],
    "12": [
        104.88566314164177,
        0
    ],
    "13": [
        127.65187177123045,
        0
    ],
    "14": [
        194.14988757180467,
        0
    ]
}