{
    "0": [
        153.79743078288638,
        0
    ],
    "1": [
        186.17522127051706,
        0
    ],
    "2": [
        105.16126171350852,
        0
    ],
    "3": [
        138.86510153646046,
        0
    ],
    "4": [
        152.44335542015003,
        0
    ],
    "5": [
        215.4315672038092,
        0
    ],
    "6": [
        88.64038098448012,
        0
    ],
    "7": [
        105.00460691950887,
        0
    ],
    "8": [
        224.5936427371466,
        0
    ],
    "9": [
        119.11008087976487,
        0
    ],
    "10": [
        122.9464368646232,
        0
    ],
    "11": [
        148.18067606413055,
        0
    ],
    "12": [
        147.188689987678,
        0
    ],
    "13": [
        142.56499520001483,
        0
    ],
    "14": [
        99.41705880144909,
        0
    ]
}