{
    "0": [
        114.75711387992526,
        0
    ],
    "1": [
        144.1005712145407,
        0
    ],
    "2": [
        177.20286688831777,
        0
    ],
    "3": [
        108.94297265985794,
        0
    ],
    "4": [
        111.83912328937215,
        0
    ],
    "5": [
        159.09631464757624,
        0
    ],
    "6": [
        205.12697393411992,
        0
    ],
    "7": [
        75.30889967246588,
        0
    ],
    "8": [
        164.24069932393408,
        0
    ],
    "9": [
        105.18513276911607,
        0
    ],
    "10": [
        184.31492616183974,
        0
    ],
    "11": [
        107.19645447462571,
        0
    ],
    "12": [
        75.78182946893311,
        0
    ],
    "13": [
        140.92993356361987,
        0
    ],
    "14": [
        167.14236890238982,
        0
    ]
}