{
    "0": [
        96.47090616124079,
        0
    ],
    "1": [
        181.64091033248664,
        0
    ],
    "2": [
        116.00807055671189,
        0
    ],
    "3": [
        121.847986829885,
        0
    ],
    "4": [
        127.09802560091148,
        0
    ],
    "5": [
        125.25564286210749,
        0
    ],
    "6": [
        88.03124469917407,
        0
    ],
    "7": [
        122.91951199367654,
        0
    ],
    "8": [
        261.3956163555843,
        0
    ],
    "9": [
        144.66872504342112,
        0
    ],
    "10": [
        85.20602038553929,
        0
    ],
    "11": [
        151.23433850247554,
        0
    ],
    "12": [
        195.93995099632684,
        0
    ],
    "13": [
        131.74263544183077,
        0
    ],
    "14": [
        177.21781696133436,
        0
    ]
}