{
    "0": [
        132.91154820554232,
        0
    ],
    "1": [
        83.95719126872041,
        0
    ],
    "2": [
        154.4780325256002,
        0
    ],
    "3": [
        156.3419744722128,
        0
    ],
    "4": [
        88.90676053937874,
        0
    ],
    "5": [
        199.24410851922363,
        0
    ],
    "6": [
        116.76359377690355,
        0
    ],
    "7": [
        129.94907562326546,
        0
    ],
    "8": [
        140.52331263543397,
        0
    ],
    "9": [
        244.04074893751041,
        0
    ],
    "10": [
        179.27729095249038,
        0
    ],
    "11": [
        132.00354929435736,
        0
    ],
    "12": [
        103.64625163818478,
        0
    ],
    "13": [
        149.79799555656302,
        0
    ],
    "14": [
        140.06679468758333,
        0
    ]
}