{
    "0": [
        116.4107533578531,
        0
    ],
    "1": [
        203.99157509159085,
        0
    ],
    "2": [
        157.34353044493005,
        0
    ],
    "3": [
        127.55948929871718,
        0
    ],
    "4": [
        197.48831720598417,
        0
    ],
    "5": [
        164.6452448329865,
        0
    ],
    "6": [
        175.56448057671386,
        0
    ],
    "7": [
        76.33289722722819,
        0
    ],
    "8": [
        154.9154235860976,
        0
    ],
    "9": [
        98.78132663610883,
        0
    ],
    "10": [
        123.43304058782965,
        0
    ],
    "11": [
        91.45370122013858,
        0
    ],
    "12": [
        181.13466377896097,
        0
    ],
    "13": [
        88.62005952771824,
        0
    ],
    "14": [
        168.9530587865999,
        0
    ]
}