{
    "0": [
        143.47283652495608,
        0
    ],
    "1": [
        104.64354365349135,
        0
    ],
    "2": [
        143.54905378823267,
        0
    ],
    "3": [
        95.49703422409286,
        0
    ],
    "4": [
        117.40678634162349,
        0
    ],
    "5": [
        126.35282679687019,
        0
    ],
    "6": [
        125.75750367565112,
        0
    ],
    "7": [
        218.20121836354068,
        0
    ],
    "8": [
        109.35979562126461,
        0
    ],
    "9": [
        121.08074717994414,
        0
    ],
    "10": [
        110.03387896105592,
        0
    ],
    "11": [
        199.7159230320129,
        0
    ],
    "12": [
        132.61839777590578,
        0
    ],
    "13": [
        121.8933262790473,
        0
    ],
    "14": [
        131.4553600992803,
        0
    ]
}