{
    "0": [
        128.04455956605233,
        0
    ],
    "1": [
        105.57846168965071,
        0
    ],
    "2": [
        236.16687349370892,
        0
    ],
    "3": [
        167.20515722021693,
        0
    ],
    "4": [
        124.2500635278721,
        0
    ],
    "5": [
        74.4189043816086,
        0
    ],
    "6": [
        136.55677438492384,
        0
    ],
    "7": [
        83.0364939665614,
        0
    ],
    "8": [
        211.69978722283255,
        0
    ],
    "9": [
        129.16030579777456,
        0
    ],
    "10": [
        148.4491811903081,
        0
    ],
    "11": [
        202.18009933589528,
        0
    ],
    "12": [
        172.09514999005015,
        0
    ],
    "13": [
        90.41179084219569,
        0
    ],
    "14": [
        91.83759764448124,
        0
    ]
}