{
    "0": [
        173.40496301368572,
        0
    ],
    "1": [
        125.07918448714642,
        0
    ],
    "2": [
        183.7324695598125,
        0
    ],
    "3": [
        178.95996126732612,
        0
    ],
    "4": [
        102.98505650054742,
        0
    ],
    "5": [
        106.0566983190583,
        0
    ],
    "6": [
        98.20713277900559,
        0
    ],
    "7": [
        213.8245504290194,
        0
    ],
    "8": [
        165.11704140436996,
        0
    ],
    "9": [
        153.33944217904224,
        0
    ],
    "10": [
        100.6314474596388,
        0
    ],
    "11": [
        168.4447547781797,
        0
    ],
    "12": [
        106.86906526008572,
        0
    ],
    "13": [
        161.2016949671934,
        0
    ],
    "14": [
        173.5507144713353,
        0
    ]
}