{
    "0": [
        164.84050489120435,
        0
    ],
    "1": [
        118.27154008827674,
        0
    ],
    "2": [
        96.13180254028053,
        0
    ],
    "3": [
        137.37396186109225,
        0
    ],
    "4": [
        114.09528027400415,
        0
    ],
    "5": [
        146.4370038593403,
        0
    ],
    "6": [
        181.84984633921462,
        0
    ],
    "7": [
        188.0588584553299,
        0
    ],
    "8": [
        106.50995063904617,
        0
    ],
    "9": [
        141.99504105886217,
        0
    ],
    "10": [
        130.12461594378968,
        0
    ],
    "11": [
        127.36585757983329,
        0
    ],
    "12": [
        117.01106174800415,
        0
    ],
    "13": [
        140.07858897436813,
        0
    ],
    "14": [
        173.36382238963503,
        0
    ]
}