{
    "0": [
        158.7719622705217,
        0
    ],
    "1": [
        139.74879635871997,
        0
    ],
    "2": [
        153.5209734919185,
        0
    ],
    "3": [
        127.89235321382918,
        0
    ],
    "4": [
        165.3756821112768,
        0
    ],
    "5": [
        131.19792266617142,
        0
    ],
    "6": [
        172.24144534268538,
        0
    ],
    "7": [
        131.78966318935446,
        0
    ],
    "8": [
        130.19582825298005,
        0
    ],
    "9": [
        121.94881798248775,
        0
    ],
    "10": [
        130.3767384915248,
        0
    ],
    "11": [
        127.39548440578571,
        0
    ],
    "12": [
        162.0110727098379,
        0
    ],
    "13": [
        144.08623436983254,
        0
    ],
    "14": [
        208.1438051981654,
        0
    ]
}