{
    "0": [
        182.60383729538756,
        0
    ],
    "1": [
        182.64648105467225,
        0
    ],
    "2": [
        175.89640752951945,
        0
    ],
    "3": [
        105.4947629248922,
        0
    ],
    "4": [
        160.19047512090512,
        0
    ],
    "5": [
        131.0216799242696,
        0
    ],
    "6": [
        173.71871520457486,
        0
    ],
    "7": [
        148.58084444220873,
        0
    ],
    "8": [
        188.60346780318628,
        0
    ],
    "9": [
        140.48714763181573,
        0
    ],
    "10": [
        118.47577689101155,
        0
    ],
    "11": [
        124.75920833260552,
        0
    ],
    "12": [
        162.90221580349058,
        0
    ],
    "13": [
        141.90760426728707,
        0
    ],
    "14": [
        166.25763629085918,
        0
    ]
}