{
    "0": [
        2.9461209122713767,
        0
    ],
    "1": [
        0.49075390510585065,
        0
    ],
    "2": [
        1.7905174854686288,
        0
    ],
    "3": [
        1.9606052637863784,
        0
    ],
    "4": [
        4.9023355084972176,
        0
    ],
    "5": [
        1.5961337158947357,
        0
    ],
    "6": [
        0.34816973013417557,
        0
    ],
    "7": [
        1.4826410067927696,
        0
    ],
    "8": [
        0.0,
        0
    ],
    "9": [
        0.0,
        0
    ],
    "10": [
        0.5507915710573958,
        0
    ],
    "11": [
        0.0,
        0
    ],
    "12": [
        1.6347793703999527,
        0
    ],
    "13": [
        0.16168419575810306,
        0
    ],
    "14": [
        2.041027978687676,
        0
    ]
}