{
    "0": [
        28.597332688787844,
        0
    ],
    "1": [
        32.363624372541345,
        0
    ],
    "2": [
        55.560550129965335,
        0
    ],
    "3": [
        62.409185878473984,
        0
    ],
    "4": [
        54.019950191869086,
        0
    ],
    "5": [
        28.595641088500855,
        0
    ],
    "6": [
        31.93072395347649,
        0
    ],
    "7": [
        41.583745081644054,
        0
    ],
    "8": [
        35.96761113255013,
        0
    ],
    "9": [
        24.59965816762958,
        0
    ],
    "10": [
        29.204786962786706,
        0
    ],
    "11": [
        59.2059443652581,
        0
    ],
    "12": [
        68.86120313911938,
        0
    ],
    "13": [
        40.42295106074673,
        0
    ],
    "14": [
        37.17911538464136,
        0
    ]
}