{
    "0": [
        148.90629179198393,
        0
    ],
    "1": [
        195.31142263900577,
        0
    ],
    "2": [
        116.37056043725471,
        0
    ],
    "3": [
        161.7874436115698,
        0
    ],
    "4": [
        179.31721469447245,
        0
    ],
    "5": [
        84.24771091380403,
        0
    ],
    "6": [
        163.3315057283221,
        0
    ],
    "7": [
        259.1688137274873,
        0
    ],
    "8": [
        150.73424783399958,
        0
    ],
    "9": [
        108.924678890696,
        0
    ],
    "10": [
        81.62166229629648,
        0
    ],
    "11": [
        124.24130208223383,
        0
    ],
    "12": [
        113.79767886312159,
        0
    ],
    "13": [
        113.80737308413124,
        0
    ],
    "14": [
        161.79440473385776,
        0
    ]
}