{
    "0": [
        91.10101454858724,
        0
    ],
    "1": [
        217.37488391318152,
        0
    ],
    "2": [
        96.88765800667106,
        0
    ],
    "3": [
        176.08302875680752,
        0
    ],
    "4": [
        136.16652643828422,
        0
    ],
    "5": [
        74.60808652586934,
        0
    ],
    "6": [
        140.39469215199927,
        0
    ],
    "7": [
        95.88280514543708,
        0
    ],
    "8": [
        109.31161092919558,
        0
    ],
    "9": [
        112.98908515159636,
        0
    ],
    "10": [
        133.75028261483442,
        0
    ],
    "11": [
        212.93934021891414,
        0
    ],
    "12": [
        177.3905568082275,
        0
    ],
    "13": [
        180.61069455341914,
        0
    ],
    "14": [
        190.4789053101214,
        0
    ]
}