{
    "0": [
        2.613742252810512,
        0
    ],
    "1": [
        3.2608187013759182,
        0
    ],
    "2": [
        0.4889887974727097,
        0
    ],
    "3": [
        0.5965884999528368,
        0
    ],
    "4": [
        0.49637155154320234,
        0
    ],
    "5": [
        1.3627928373049332,
        0
    ],
    "6": [
        1.5613226541480107,
        0
    ],
    "7": [
        0.0,
        0
    ],
    "8": [
        2.2389878050425907,
        0
    ],
    "9": [
        0.43921515221082535,
        0
    ],
    "10": [
        3.3135003140182278,
        0
    ],
    "11": [
        0.0,
        0
    ],
    "12": [
        1.2296298854468275,
        0
    ],
    "13": [
        1.420021057496891,
        0
    ],
    "14": [
        1.1962864044662356,
        0
    ]
}