{
    "0": [
        68.08139761833942,
        0
    ],
    "1": [
        46.48744084130827,
        0
    ],
    "2": [
        53.920830675782334,
        0
    ],
    "3": [
        31.464252012362614,
        0
    ],
    "4": [
        93.43128272545684,
        0
    ],
    "5": [
        82.05753806133043,
        0
    ],
    "6": [
        64.91574103456598,
        0
    ],
    "7": [
        40.781445112628454,
        0
    ],
    "8": [
        78.89192804800734,
        0
    ],
    "9": [
        68.63434245635352,
        0
    ],
    "10": [
        92.83629918524271,
        0
    ],
    "11": [
        63.73456582611672,
        0
    ],
    "12": [
        88.64969700353393,
        0
    ],
    "13": [
        95.02865914744528,
        0
    ],
    "14": [
        60.978147145880904,
        0
    ]
}