{
    "0": [
        36.99584377666231,
        0
    ],
    "1": [
        52.185483178575964,
        0
    ],
    "2": [
        77.51840427869766,
        0
    ],
    "3": [
        94.669320123133,
        0
    ],
    "4": [
        60.034609625322595,
        0
    ],
    "5": [
        53.840736564811984,
        0
    ],
    "6": [
        67.23105221823894,
        0
    ],
    "7": [
        63.95834307395746,
        0
    ],
    "8": [
        44.480376403234494,
        0
    ],
    "9": [
        39.9895090423028,
        0
    ],
    "10": [
        61.286637688970465,
        0
    ],
    "11": [
        67.89252667610134,
        0
    ],
    "12": [
        83.1094446717277,
        0
    ],
    "13": [
        65.24228275094322,
        0
    ],
    "14": [
        54.3630806926725,
        0
    ]
}