{
    "0": [
        98.20819357768487,
        0
    ],
    "1": [
        230.9907481058814,
        0
    ],
    "2": [
        217.40021071697907,
        0
    ],
    "3": [
        181.22094456203828,
        0
    ],
    "4": [
        222.09729004891523,
        0
    ],
    "5": [
        254.31190845382022,
        0
    ],
    "6": [
        191.80085639198268,
        0
    ],
    "7": [
        157.77559668502866,
        0
    ],
    "8": [
        201.03489905351188,
        0
    ],
    "9": [
        278.91022122229424,
        0
    ],
    "10": [
        129.6891556959613,
        0
    ],
    "11": [
        146.167303709279,
        0
    ],
    "12": [
        164.12367781704958,
        0
    ],
    "13": [
        134.93024995250377,
        0
    ],
    "14": [
        124.30601832533348,
        0
    ]
}