{
    "0": [
        186.22410231533226,
        0
    ],
    "1": [
        172.27464681296647,
        0
    ],
    "2": [
        154.25809448438525,
        0
    ],
    "3": [
        164.91678751832234,
        0
    ],
    "4": [
        110.48659656718225,
        0
    ],
    "5": [
        215.08237815441,
        0
    ],
    "6": [
        237.79430726609812,
        0
    ],
    "7": [
        154.28161243658647,
        0
    ],
    "8": [
        119.68690200891744,
        0
    ],
    "9": [
        125.62185833092187,
        0
    ],
    "10": [
        298.0555118303431,
        0
    ],
    "11": [
        241.56474055724223,
        0
    ],
    "12": [
        118.61050617506015,
        0
    ],
    "13": [
        192.3079805923307,
        0
    ],
    "14": [
        195.77418644246106,
        0
    ]
}