{
    "0": [
        216.43622913618822,
        0
    ],
    "1": [
        172.512992813536,
        0
    ],
    "2": [
        99.81753088431182,
        0
    ],
    "3": [
        178.31052965793265,
        0
    ],
    "4": [
        211.64683427351295,
        0
    ],
    "5": [
        330.89371613675866,
        0
    ],
    "6": [
        92.15516990237843,
        0
    ],
    "7": [
        305.7896063102214,
        0
    ],
    "8": [
        128.539233233926,
        0
    ],
    "9": [
        151.21015972982036,
        0
    ],
    "10": [
        137.77796737085484,
        0
    ],
    "11": [
        272.41495457798226,
        0
    ],
    "12": [
        229.39455152636998,
        0
    ],
    "13": [
        190.31986826543692,
        0
    ],
    "14": [
        283.21141171666227,
        0
    ]
}