{
    "0": [
        2.287061944942337,
        0
    ],
    "1": [
        3.4578822395269513,
        0
    ],
    "2": [
        1.166152307346514,
        0
    ],
    "3": [
        0.0,
        0
    ],
    "4": [
        1.1591600085444482,
        0
    ],
    "5": [
        0.0,
        0
    ],
    "6": [
        1.6885978434480549,
        0
    ],
    "7": [
        0.0,
        0
    ],
    "8": [
        1.1049844689205428,
        0
    ],
    "9": [
        1.8884138971426634,
        0
    ],
    "10": [
        3.612259506747795,
        0
    ],
    "11": [
        0.0,
        0
    ],
    "12": [
        1.9103128098954976,
        0
    ],
    "13": [
        2.0269149784406415,
        0
    ],
    "14": [
        2.8264269037582492,
        0
    ]
}