{
    "0": [
        0.2486144820712414,
        0
    ],
    "1": [
        0.7156041475220769,
        0
    ],
    "2": [
        0.9395580448946055,
        0
    ],
    "3": [
        0.7463239729586938,
        0
    ],
    "4": [
        2.7813026056100205,
        0
    ],
    "5": [
        0.49402395181191194,
        0
    ],
    "6": [
        1.0854787774307006,
        0
    ],
    "7": [
        4.307100558702928,
        0
    ],
    "8": [
        0.0,
        0
    ],
    "9": [
        2.9716754026862424,
        0
    ],
    "10": [
        0.6765693528742355,
        0
    ],
    "11": [
        1.3201552455987966,
        0
    ],
    "12": [
        3.2938976718034794,
        0
    ],
    "13": [
        2.3651228373211115,
        0
    ],
    "14": [
        0.10649988428001937,
        0
    ]
}