{
    "0": [
        3.341286144321011,
        0
    ],
    "1": [
        0.44683232344268936,
        0
    ],
    "2": [
        0.5418966682757118,
        0
    ],
    "3": [
        1.2787608795028647,
        0
    ],
    "4": [
        0.6462080071958052,
        0
    ],
    "5": [
        2.8033408607019483,
        0
    ],
    "6": [
        2.0063087761326517,
        0
    ],
    "7": [
        3.779744398953306,
        0
    ],
    "8": [
        3.079448810450929,
        0
    ],
    "9": [
        0.6639811321103891,
        0
    ],
    "10": [
        4.9142763577152735,
        0
    ],
    "11": [
        2.3767934702815454,
        0
    ],
    "12": [
        3.1687641429858884,
        0
    ],
    "13": [
        0.0,
        0
    ],
    "14": [
        0.3387325779801742,
        0
    ]
}