{
    "0": [
        1.8159247184730882,
        0
    ],
    "1": [
        4.6933994182469085,
        0
    ],
    "2": [
        3.6815703334875125,
        0
    ],
    "3": [
        3.699362202561142,
        0
    ],
    "4": [
        2.9611787128561575,
        0
    ],
    "5": [
        0.0,
        0
    ],
    "6": [
        0.7937978342519381,
        0
    ],
    "7": [
        3.2255619632676815,
        0
    ],
    "8": [
        0.27579275930233477,
        0
    ],
    "9": [
        1.6980086035096684,
        0
    ],
    "10": [
        0.0,
        0
    ],
    "11": [
        3.361569402615049,
        0
    ],
    "12": [
        0.0,
        0
    ],
    "13": [
        1.4677387299430513,
        0
    ],
    "14": [
        1.1892205365466293,
        0
    ]
}