{
    "0": [
        2.542671880030749,
        0
    ],
    "1": [
        0.9094498433581755,
        0
    ],
    "2": [
        1.1310975673672823,
        0
    ],
    "3": [
        3.7806935051759196,
        0
    ],
    "4": [
        3.336610178817488,
        0
    ],
    "5": [
        3.4852490099640088,
        0
    ],
    "6": [
        1.091953933934131,
        0
    ],
    "7": [
        0.0,
        0
    ],
    "8": [
        2.2013386133871617,
        0
    ],
    "9": [
        1.8381886104675795,
        0
    ],
    "10": [
        0.5097975885250388,
        0
    ],
    "11": [
        2.488362697123771,
        0
    ],
    "12": [
        1.6860967296460265,
        0
    ],
    "13": [
        0.0,
        0
    ],
    "14": [
        0.0,
        0
    ]
}