{
    "0": [
        40.43623652634469,
        0
    ],
    "1": [
        54.27374327806454,
        0
    ],
    "2": [
        23.78324551081698,
        0
    ],
    "3": [
        47.820934601224806,
        0
    ],
    "4": [
        47.60339946717366,
        0
    ],
    "5": [
        63.92854984839684,
        0
    ],
    "6": [
        62.84802207221831,
        0
    ],
    "7": [
        54.3087302104235,
        0
    ],
    "8": [
        33.448286072929726,
        0
    ],
    "9": [
        36.40595633406027,
        0
    ],
    "10": [
        39.79999423911431,
        0
    ],
    "11": [
        32.37925022474819,
        0
    ],
    "12": [
        39.97759578959254,
        0
    ],
    "13": [
        40.9083058484617,
        0
    ],
    "14": [
        42.596620284377956,
        0
    ]
}