{
    "0": [
        181.41148231843596,
        0
    ],
    "1": [
        94.72706277689964,
        0
    ],
    "2": [
        183.5895374981108,
        0
    ],
    "3": [
        188.903552997407,
        0
    ],
    "4": [
        173.35460030926973,
        0
    ],
    "5": [
        85.52854916231266,
        0
    ],
    "6": [
        163.83557766547767,
        0
    ],
    "7": [
        77.6443416790315,
        0
    ],
    "8": [
        88.92045506824273,
        0
    ],
    "9": [
        129.11348655129834,
        0
    ],
    "10": [
        178.75036588655996,
        0
    ],
    "11": [
        96.46244099890937,
        0
    ],
    "12": [
        114.77915254320722,
        0
    ],
    "13": [
        132.14929253048,
        0
    ],
    "14": [
        94.73608602114903,
        0
    ]
}