{
    "0": [
        107.96794043001165,
        0
    ],
    "1": [
        144.73371272317274,
        0
    ],
    "2": [
        130.20630986965637,
        0
    ],
    "3": [
        106.24729308964774,
        0
    ],
    "4": [
        122.7853899229501,
        0
    ],
    "5": [
        180.78933257684105,
        0
    ],
    "6": [
        150.98352813440067,
        0
    ],
    "7": [
        166.16517455007397,
        0
    ],
    "8": [
        172.82738301479705,
        0
    ],
    "9": [
        146.08695709758538,
        0
    ],
    "10": [
        119.10521630565906,
        0
    ],
    "11": [
        146.42751104951006,
        0
    ],
    "12": [
        157.92993334969418,
        0
    ],
    "13": [
        89.01607532462681,
        0
    ],
    "14": [
        156.3210964389501,
        0
    ]
}