{
    "0": [
        150.4468724182932,
        0
    ],
    "1": [
        125.50703363969363,
        0
    ],
    "2": [
        207.4517159984812,
        0
    ],
    "3": [
        118.33182511807148,
        0
    ],
    "4": [
        164.15531167748108,
        0
    ],
    "5": [
        140.78966593045882,
        0
    ],
    "6": [
        84.73886934116027,
        0
    ],
    "7": [
        99.21156675869607,
        0
    ],
    "8": [
        143.2702102265623,
        0
    ],
    "9": [
        139.6631043225683,
        0
    ],
    "10": [
        138.6295677626326,
        0
    ],
    "11": [
        154.52345096568587,
        0
    ],
    "12": [
        104.38087683302321,
        0
    ],
    "13": [
        150.85771017339954,
        0
    ],
    "14": [
        160.3992547598994,
        0
    ]
}