{
    "0": [
        188.06071308040893,
        0
    ],
    "1": [
        105.69020453318902,
        0
    ],
    "2": [
        166.71570050233316,
        0
    ],
    "3": [
        85.97851067122532,
        0
    ],
    "4": [
        186.19229035950798,
        0
    ],
    "5": [
        123.16978780768987,
        0
    ],
    "6": [
        200.98139401661345,
        0
    ],
    "7": [
        170.03812664519424,
        0
    ],
    "8": [
        156.0482436856402,
        0
    ],
    "9": [
        175.99335156405,
        0
    ],
    "10": [
        178.73895592423355,
        0
    ],
    "11": [
        152.84253767953396,
        0
    ],
    "12": [
        143.88445358688944,
        0
    ],
    "13": [
        148.9028736080461,
        0
    ],
    "14": [
        124.63521669536125,
        0
    ]
}