{
    "0": [
        0.0,
        0
    ],
    "1": [
        1.8088082012983646,
        0
    ],
    "2": [
        1.801079467704823,
        0
    ],
    "3": [
        0.0,
        0
    ],
    "4": [
        0.33649201082864966,
        0
    ],
    "5": [
        2.4260710745009293,
        0
    ],
    "6": [
        0.11290461869613665,
        0
    ],
    "7": [
        0.0,
        0
    ],
    "8": [
        2.037140401143057,
        0
    ],
    "9": [
        7.110672032667047,
        0
    ],
    "10": [
        0.0,
        0
    ],
    "11": [
        2.8705888800941497,
        0
    ],
    "12": [
        1.7657359493807445,
        0
    ],
    "13": [
        2.6310529074814326,
        0
    ],
    "14": [
        4.471847167277539,
        0
    ]
}