{
    "0": [
        61.73126626890437,
        0
    ],
    "1": [
        77.26318788643385,
        0
    ],
    "2": [
        59.95976015175606,
        0
    ],
    "3": [
        53.649010645821825,
        0
    ],
    "4": [
        55.70444895098681,
        0
    ],
    "5": [
        96.8733164451143,
        0
    ],
    "6": [
        76.04909936837261,
        0
    ],
    "7": [
        64.7666288028835,
        0
    ],
    "8": [
        68.61268117878426,
        0
    ],
    "9": [
        90.17578215154253,
        0
    ],
    "10": [
        54.82666777948447,
        0
    ],
    "11": [
        43.363180455945134,
        0
    ],
    "12": [
        51.22162409279548,
        0
    ],
    "13": [
        83.25123925562492,
        0
    ],
    "14": [
        60.44521007870723,
        0
    ]
}